python_rucaptcha/CallbackClient.py
python_rucaptcha/CapyPuzzle.py
python_rucaptcha/DistilCaptcha.py
python_rucaptcha/FunCaptcha.py
python_rucaptcha/GeeTest.py
python_rucaptcha/HCaptcha.py
python_rucaptcha/ImageCaptcha.py
python_rucaptcha/KeyCaptcha.py
python_rucaptcha/ReCaptchaV2.py
python_rucaptcha/ReCaptchaV3.py
python_rucaptcha/RotateCaptcha.py
python_rucaptcha/RuCaptchaControl.py
python_rucaptcha/TextCaptcha.py
python_rucaptcha/config.py
python_rucaptcha/decorators.py
python_rucaptcha/result_handler.py
python_rucaptcha_session_patch-3.0.dist-info/LICENSE
python_rucaptcha_session_patch-3.0.dist-info/METADATA
python_rucaptcha_session_patch-3.0.dist-info/WHEEL
python_rucaptcha_session_patch-3.0.dist-info/top_level.txt
python_rucaptcha_session_patch-3.0.dist-info/RECORD
