Metadata-Version: 2.1
Name: python-rucaptcha-session-patch
Version: 3.0
Summary: Python 3.6+ RuCaptcha library with AIO module.
Home-page: https://github.com/AndreiDrang/python-rucaptcha
Author: AndreiDrang, redV0ID, MaximumQuiet
Author-email: drang.andray@gmail.com
License: AGPL-3.0
Keywords: captcha
Platform: UNKNOWN
Classifier: License :: OSI Approved :: GNU Affero General Public License v3 or later (AGPLv3+)
Classifier: Programming Language :: Python
Classifier: Programming Language :: Python :: 3.6
Classifier: Development Status :: 5 - Production/Stable
Classifier: Framework :: AsyncIO
Classifier: Operating System :: Unix
Classifier: Operating System :: Microsoft :: Windows
Classifier: Operating System :: MacOS
Requires-Python: >=3.6.0
Requires-Dist: requests (==2.23.0)
Requires-Dist: aiohttp (==3.6.2)
Requires-Dist: pika (==1.1.0)
